drug_named_entity_recognition/__init__.py
drug_named_entity_recognition/drug_ner_dictionary.pkl.bz2
drug_named_entity_recognition/drugs_finder.py
drug_named_entity_recognition/molecular_properties.py
drug_named_entity_recognition/omop_api.py
drug_named_entity_recognition/structure_file_downloader.py
drug_named_entity_recognition/util.py
drug_named_entity_recognition-2.0.9.dist-info/licenses/LICENSE
drug_named_entity_recognition-2.0.9.dist-info/METADATA
drug_named_entity_recognition-2.0.9.dist-info/WHEEL
drug_named_entity_recognition-2.0.9.dist-info/top_level.txt
drug_named_entity_recognition-2.0.9.dist-info/RECORD
