Metadata-Version: 2.4
Name: drug-named-entity-recognition
Version: 2.0.9
Summary: Drug Named Entity Recognition library to find and resolve drug names in a string (drug named entity linking)
Home-page: https://fastdatascience.com/drug-named-entity-recognition-python-library
Author: Thomas Wood
Author-email: Thomas Wood <thomas@fastdatascience.com>
Maintainer-email: Thomas Wood <thomas@fastdatascience.com>
License: MIT License
Project-URL: Documentation, https://fastdatascience.com/drug-named-entity-recognition-python-library/
Project-URL: Bug Reports, https://github.com/fastdatascience/drug_named_entity_recognition/issues
Project-URL: Source Code, https://github.com/fastdatascience/drug_named_entity_recognition
Keywords: drug,bio,biomedical,medical,pharma,pharmaceutical,ner,nlp,named entity recognition,natural language processing,named entity linking
Classifier: Development Status :: 5 - Production/Stable
Classifier: Intended Audience :: Developers
Classifier: Topic :: Software Development :: Build Tools
Classifier: Programming Language :: Python :: 3
Classifier: Programming Language :: Python :: 3.6
Classifier: Programming Language :: Python :: 3.7
Classifier: Programming Language :: Python :: 3.8
Classifier: Programming Language :: Python :: 3.9
Classifier: Programming Language :: Python :: 3.10
Classifier: Programming Language :: Python :: 3.11
Classifier: Programming Language :: Python :: 3.12
Classifier: Programming Language :: Python :: 3.13
Classifier: Programming Language :: Python :: 3 :: Only
Classifier: License :: OSI Approved :: MIT License
Classifier: Operating System :: OS Independent
Requires-Python: >=3.6
License-File: LICENSE
Requires-Dist: requests
Provides-Extra: dev
Requires-Dist: check-manifest; extra == "dev"
Requires-Dist: pytest; extra == "dev"
Requires-Dist: nltk; extra == "dev"
Requires-Dist: pandas; extra == "dev"
Dynamic: author
Dynamic: home-page
Dynamic: license-file
Dynamic: requires-python
